mailigen/__init__.py
mailigen/mgapi_apikeyAdd.py
mailigen/mgapi_apikeyExpire.py
mailigen/mgapi_apikeys.py
mailigen/mgapi_campaignBounceMessages.py
mailigen/mgapi_campaignClickStats.py
mailigen/mgapi_campaignCreate.py
mailigen/mgapi_campaignDelete.py
mailigen/mgapi_campaignEmailDomainPerformance.py
mailigen/mgapi_campaignForwardStats.py
mailigen/mgapi_campaignGeoOpens.py
mailigen/mgapi_campaignHardBounces.py
mailigen/mgapi_campaignPause.py
mailigen/mgapi_campaignReplicate.py
mailigen/mgapi_campaignResume.py
mailigen/mgapi_campaignSchedule.py
mailigen/mgapi_campaignSendNow.py
mailigen/mgapi_campaignSendTest.py
mailigen/mgapi_campaignSoftBounces.py
mailigen/mgapi_campaignStats.py
mailigen/mgapi_campaignTemplates.py
mailigen/mgapi_campaignUnschedule.py
mailigen/mgapi_campaignUnsubscribes.py
mailigen/mgapi_campaignUpdate.py
mailigen/mgapi_campaigns.py
mailigen/mgapi_getAccountDetails.py
mailigen/mgapi_listBatchSubscribe.py
mailigen/mgapi_listBatchUnsubscribe.py
mailigen/mgapi_listGrowthHistory.py
mailigen/mgapi_listMemberInfo.py
mailigen/mgapi_listMembers.py
mailigen/mgapi_listMergeVarAdd.py
mailigen/mgapi_listMergeVarDel.py
mailigen/mgapi_listMergeVarUpdate.py
mailigen/mgapi_listMergeVars.py
mailigen/mgapi_listSubscribe.py
mailigen/mgapi_listUnsubscribe.py
mailigen/mgapi_listUpdateMember.py
mailigen/mgapi_lists.py
mailigen/mgapi_listsForEmail.py
mailigen/mgapi_login.py
mailigen/mgapi_ping.py
mailigen/setup.py
mailigen/examples/__init__.py
mailigen/examples/mgapi_apikeyAdd.py
mailigen/examples/mgapi_apikeyExpire.py
mailigen/examples/mgapi_apikeys.py
mailigen/examples/mgapi_campaignBounceMessages.py
mailigen/examples/mgapi_campaignClickStats.py
mailigen/examples/mgapi_campaignCreate.py
mailigen/examples/mgapi_campaignDelete.py
mailigen/examples/mgapi_campaignEmailDomainPerformance.py
mailigen/examples/mgapi_campaignForwardStats.py
mailigen/examples/mgapi_campaignGeoOpens.py
mailigen-1.0.dist-info/METADATA
mailigen-1.0.dist-info/RECORD
mailigen-1.0.dist-info/WHEEL
mailigen-1.0.dist-info/top_level.txt
